approved/__init__.py
approved/cli.py
approved/parse/__init__.py
approved/parse/cli.py
approved/parse/mip.py
approved/store/__init__.py
approved/store/cli.py
approved/store/models.py
approved-0.0.1.dist-info/DESCRIPTION.rst
approved-0.0.1.dist-info/METADATA
approved-0.0.1.dist-info/RECORD
approved-0.0.1.dist-info/WHEEL
approved-0.0.1.dist-info/entry_points.txt
approved-0.0.1.dist-info/metadata.json
approved-0.0.1.dist-info/top_level.txt
