Metadata-Version: 2.0
Name: approved
Version: 0.0.1
Summary: Store QC metrics from sequencing analyses
Home-page: UNKNOWN
Author: Robin Andeer
Author-email: robin.andeer@scilifelab.se
License: BSD License
Keywords: pytest cli
Platform: any
Classifier: Development Status :: 3 - Alpha
Classifier: License :: OSI Approved :: BSD License
Classifier: Operating System :: OS Independent
Classifier: Programming Language :: Python
Classifier: Programming Language :: Python :: 2
Classifier: Programming Language :: Python :: 2.7
Classifier: Programming Language :: Python :: 3
Classifier: Programming Language :: Python :: 3.3
Requires-Dist: alchy
Requires-Dist: alembic
Requires-Dist: click
